aily_core/__init__.py
aily_core/action/__init__.py
aily_core/action/call_action.py
aily_core/common/context.py
aily_core/common/util.py
aily_core/credential/__init__.py
aily_core/credential/credential.py
aily_core/env/__init__.py
aily_core/env/get_env_info.py
aily_core/message/builder.py
aily_core/message/components/__init__.py
aily_core/message/components/base_component.py
aily_core/message/components/button.py
aily_core/message/components/chart.py
aily_core/message/components/code.py
aily_core/message/components/col.py
aily_core/message/components/color_text.py
aily_core/message/components/data_record.py
aily_core/message/components/highlight.py
aily_core/message/components/image.py
aily_core/message/components/item_list.py
aily_core/message/components/link.py
aily_core/message/components/mention.py
aily_core/message/components/note.py
aily_core/message/components/ordered_list.py
aily_core/message/components/row.py
aily_core/message/components/table.py
aily_core/message/components/title.py
aily_core-0.1.0b10.dist-info/LICENSE
aily_core-0.1.0b10.dist-info/METADATA
aily_core-0.1.0b10.dist-info/WHEEL
aily_core-0.1.0b10.dist-info/RECORD
